odoo/addons/sale_missing_tracking/README.rst
odoo/addons/sale_missing_tracking/__init__.py
odoo/addons/sale_missing_tracking/__manifest__.py
odoo/addons/sale_missing_tracking/data/mail_activity_data.xml
odoo/addons/sale_missing_tracking/data/mail_data.xml
odoo/addons/sale_missing_tracking/data/mail_template_data.xml
odoo/addons/sale_missing_tracking/data/sale_missing_tracking_data.xml
odoo/addons/sale_missing_tracking/i18n/es.po
odoo/addons/sale_missing_tracking/i18n/sale_missing_tracking.pot
odoo/addons/sale_missing_tracking/models/__init__.py
odoo/addons/sale_missing_tracking/models/product.py
odoo/addons/sale_missing_tracking/models/res_company.py
odoo/addons/sale_missing_tracking/models/res_config_settings.py
odoo/addons/sale_missing_tracking/models/res_partner.py
odoo/addons/sale_missing_tracking/models/sale_missing_tracking.py
odoo/addons/sale_missing_tracking/models/sale_missing_tracking_exception.py
odoo/addons/sale_missing_tracking/models/sale_order.py
odoo/addons/sale_missing_tracking/readme/CONFIGURE.rst
odoo/addons/sale_missing_tracking/readme/CONTRIBUTORS.rst
odoo/addons/sale_missing_tracking/readme/DESCRIPTION.rst
odoo/addons/sale_missing_tracking/readme/USAGE.rst
odoo/addons/sale_missing_tracking/security/ir.model.access.csv
odoo/addons/sale_missing_tracking/security/security.xml
odoo/addons/sale_missing_tracking/static/description/icon.png
odoo/addons/sale_missing_tracking/static/description/index.html
odoo/addons/sale_missing_tracking/tests/__init__.py
odoo/addons/sale_missing_tracking/tests/test_sale_missing_tracking.py
odoo/addons/sale_missing_tracking/views/product_views.xml
odoo/addons/sale_missing_tracking/views/res_config_settings_views.xml
odoo/addons/sale_missing_tracking/views/res_partner_views.xml
odoo/addons/sale_missing_tracking/views/sale_missing_tracking_exception_views.xml
odoo/addons/sale_missing_tracking/views/sale_missing_tracking_menu.xml
odoo/addons/sale_missing_tracking/views/sale_missing_tracking_reason_views.xml
odoo_addon_sale_missing_tracking-15.0.1.0.2.1.dist-info/METADATA
odoo_addon_sale_missing_tracking-15.0.1.0.2.1.dist-info/WHEEL
odoo_addon_sale_missing_tracking-15.0.1.0.2.1.dist-info/top_level.txt
odoo_addon_sale_missing_tracking-15.0.1.0.2.1.dist-info/RECORD
